rom.sv
module rom #(
    parameter ADDRESS_WIDTH = 8,
                DATA_WIDTH = 8
)(
    input logic clk,
    input logic [ADDRESS_WIDTH-1:0] offset,
    input logic [ADDRESS_WIDTH-1:0] addr1,
    input logic [ADDRESS_WIDTH-1:0] addr2, //[7:0]
    output logic [DATA_WIDTH-1:0] data1, //[7:0]
    output logic [DATA_WIDTH-1:0] data2
);
logic [DATA_WIDTH-1:0] rom_array [2**ADDRESS_WIDTH-1:0]; //[2^8-1=255:0 mem locations]
initial begin
    $display("Loading rom.");
    $readmemh("sinerom.mem", rom_array);
end;

always_ff @(posedge clk)
    data1 <= rom_array [addr1];
always_ff @(posedge clk)
    data2 <= rom_array [addr2];

endmodule

counter.sv
module counter #(
    parameter WIDTH=8
)(
    //interface signals
    input logic clk,
    input logic rst,
    input logic en,
    input logic [WIDTH-1:0] incr,
    output logic [WIDTH-1:0] count
);

always_ff@(posedge clk)
    if (rst) count <= {WIDTH{1'b0}};
    //else if (en) count <= count+incr;
    else count<=count;
endmodule

sinegen.sv
module sinegen# (
    parameter A_WIDTH = 8, //8 bit adress/data width
                D_WIDTH = 8
)(

    input logic [A_WIDTH-1:0] incr, //input
    input logic clk,
    input logic rst,
    input logic en,
    output logic [A_WIDTH-1:0] data1,
    output logic [A_WIDTH-1:0] data2//output data
);

    logic [A_WIDTH-1:0] address;

counter addrCounter (
    .clk (clk),
    .rst (rst),
    .en (en),
    //.incr (incr),
    .count (address)
);

rom sineRom (
    .clk (clk),
    .addr1 (address),
    .addr2 (address+incr),
    .data1 (data1),
    .data2 (data2)
);

endmodule

sinegen.vcd
$version Generated by VerilatedVcd $end
$date Wed Nov  2 13:52:24 2022 $end
$timescale 1ps $end

 $scope module TOP $end
  $var wire  1 $ clk $end
  $var wire  8 ' data1 [7:0] $end
  $var wire  8 ( data2 [7:0] $end
  $var wire  1 & en $end
  $var wire  8 # incr [7:0] $end
  $var wire  1 % rst $end
  $scope module sinegen $end
   $var wire 32 + A_WIDTH [31:0] $end
   $var wire 32 + D_WIDTH [31:0] $end
   $var wire  8 ) address [7:0] $end
   $var wire  1 $ clk $end
   $var wire  8 ' data1 [7:0] $end
   $var wire  8 ( data2 [7:0] $end
   $var wire  1 & en $end
   $var wire  8 # incr [7:0] $end
   $var wire  1 % rst $end
   $scope module addrCounter $end
    $var wire 32 + WIDTH [31:0] $end
    $var wire  1 $ clk $end
    $var wire  8 ) count [7:0] $end
    $var wire  1 & en $end
    $var wire  8 , incr [7:0] $end
    $var wire  1 % rst $end
   $upscope $end
   $scope module sineRom $end
    $var wire 32 + ADDRESS_WIDTH [31:0] $end
    $var wire 32 + DATA_WIDTH [31:0] $end
    $var wire  8 ) addr1 [7:0] $end
    $var wire  8 * addr2 [7:0] $end
    $var wire  1 $ clk $end
    $var wire  8 ' data1 [7:0] $end
    $var wire  8 ( data2 [7:0] $end
    $var wire  8 - offset [7:0] $end
   $upscope $end
  $upscope $end
 $upscope $end
$enddefinitions $end


#0
b00000001 #
1$
0%
1&
b00000000 '
b00000000 (
b00000000 )
b00000001 *
b00000000000000000000000000001000 +
b00000000 ,
b00000000 -
#1
0$
#2
b00011000 #
1$
b11111110 '
b11111101 (
b00011000 *
#3
0$
#4
1$
b11101000 (
#5
0$
#6
1$
#7
0$
#8
1$
#9
0$
#10
1$
#11
0$
#12
1$
#13
0$
#14
1$
#15
0$
#16
1$
#17
0$
#18
1$
#19
0$
#20
1$
#21
0$
#22
1$
#23
0$
#24
1$
#25
0$
#26
1$
#27
0$
#28
1$
#29
0$
#30
1$
#31
0$
#32
1$
#33
0$
#34
1$
#35
0$
#36
1$
#37
0$
#38
1$
#39
0$
#40
1$
#41
0$
#42
1$
#43
0$
#44
1$
#45
0$
#46
1$
#47
0$
#48
1$
#49
0$
#50
1$
#51
0$
#52
1$
#53
0$
#54
1$
#55
0$
#56
1$
#57
0$
#58
1$
#59
0$
#60
1$
#61
0$
#62
1$
#63
0$
#64
1$
#65
0$
#66
1$
#67
0$
#68
1$
#69
0$
#70
1$
#71
0$
#72
1$
#73
0$
#74
1$
#75
0$
#76
1$
#77
0$
#78
1$
#79
0$
#80
1$
#81
0$
#82
1$
#83
0$
#84
1$
#85
0$
#86
1$
#87
0$
#88
1$
#89
0$
#90
1$
#91
0$
#92
1$
#93
0$
#94
1$
#95
0$
#96
1$
#97
0$
#98
1$
#99
0$
#100
1$
#101
0$
#102
1$
#103
0$
#104
1$
#105
0$
#106
1$
#107
0$
#108
1$
#109
0$
#110
1$
#111
0$
#112
1$
#113
0$
#114
1$
#115
0$
#116
1$
#117
0$
#118
1$
#119
0$
#120
1$
#121
0$
#122
1$
#123
0$
#124
1$
#125
0$
#126
1$
#127
0$
#128
1$
#129
0$
#130
1$
#131
0$
#132
1$
#133
0$
#134
1$
#135
0$
#136
b00011001 #
1$
b00011001 *
#137
0$
#138
b00011010 #
1$
b11100110 (
b00011010 *
#139
0$
#140
b00011011 #
1$
b11100101 (
b00011011 *
#141
0$
#142
1$
b11100011 (
#143
0$
#144
b00011100 #
1$
b00011100 *
#145
0$
#146
1$
b11100001 (
#147
0$
#148
1$
#149
0$
#150
1$
#151
0$
#152
1$
#153
0$
#154
1$
#155
0$
#156
b00011101 #
1$
b00011101 *
#157
0$
#158
1$
b11011111 (
#159
0$
#160
1$
#161
0$
#162
1$
#163
0$
#164
b00011110 #
1$
b00011110 *
#165
0$
#166
1$
b11011101 (
#167
0$
#168
1$
#169
0$
#170
1$
#171
0$
#172
1$
#173
0$
#174
1$
#175
0$
#176
1$
#177
0$
#178
1$
#179
0$
#180
1$
#181
0$
#182
1$
#183
0$
#184
1$
#185
0$
#186
1$
#187
0$
#188
1$
#189
0$
#190
1$
#191
0$
#192
1$
#193
0$
#194
1$
#195
0$
#196
1$
#197
0$
#198
b00011111 #
1$
b00011111 *
#199
0$
#200
b00100011 #
1$
b11011010 (
b00100011 *
#201
0$
#202
b00100111 #
1$
b11010001 (
b00100111 *
#203
0$
#204
1$
b11001000 (
#205
0$
#206
1$
#207
0$
#208
1$
#209
0$
#210
1$
#211
0$
#212
1$
#213
0$
#214
1$
#215
0$
#216
1$
#217
0$
#218
1$
#219
0$
#220
1$
#221
0$
#222
1$
#223
0$
#224
1$
#225
0$
#226
1$
#227
0$
#228
1$
#229
0$
#230
1$
#231
0$
#232
1$
#233
0$
#234
1$
#235
0$
#236
1$
#237
0$
#238
1$
#239
0$
#240
1$
#241
0$
#242
b00101001 #
1$
b00101001 *
#243
0$
#244
b00101100 #
1$
b11000010 (
b00101100 *
#245
0$
#246
b00101111 #
1$
b10111010 (
b00101111 *
#247
0$
#248
b00110000 #
1$
b10110010 (
b00110000 *
#249
0$
#250
1$
b10101111 (
#251
0$
#252
1$
#253
0$
#254
1$
#255
0$
#256
1$
#257
0$
#258
1$
#259
0$
#260
1$
#261
0$
#262
1$
#263
0$
#264
1$
#265
0$
#266
1$
#267
0$
#268
1$
#269
0$
#270
1$
#271
0$
#272
1$
#273
0$
#274
b00110001 #
1$
b00110001 *
#275
0$
#276
b00110011 #
1$
b10101100 (
b00110011 *
#277
0$
#278
b00110100 #
1$
b10100110 (
b00110100 *
#279
0$
#280
b00110110 #
1$
b10100011 (
b00110110 *
#281
0$
#282
b00111010 #
1$
b10011101 (
b00111010 *
#283
0$
#284
b00111100 #
1$
b10010001 (
b00111100 *
#285
0$
#286
1$
b10001011 (
#287
0$
#288
1$
#289
0$
#290
1$
#291
0$
#292
1$
#293
0$
#294
1$
#295
0$
#296
1$
#297
0$
#298
1$
#299
0$
#300
1$
#301
0$
#302
1$
#303
0$
#304
1$
#305
0$
#306
b00111101 #
1$
b00111101 *
#307
0$
#308
b00111111 #
1$
b10001000 (
b00111111 *
#309
0$
#310
b01000000 #
1$
b10000010 (
b01000000 *
#311
0$
#312
b01000001 #
1$
b01111110 (
b01000001 *
#313
0$
#314
b01000011 #
1$
b01111011 (
b01000011 *
#315
0$
#316
b01000110 #
1$
b01110101 (
b01000110 *
#317
0$
#318
1$
b01101100 (
#319
0$
#320
1$
#321
0$
#322
1$
#323
0$
#324
1$
#325
0$
#326
1$
#327
0$
#328
1$
#329
0$
#330
1$
#331
0$
#332
1$
#333
0$
#334
1$
#335
0$
#336
1$
#337
0$
#338
1$
#339
0$
#340
b01000111 #
1$
b01000111 *
#341
0$
#342
b01001001 #
1$
b01101001 (
b01001001 *
#343
0$
#344
b01001011 #
1$
b01100011 (
b01001011 *
#345
0$
#346
b01001100 #
1$
b01011101 (
b01001100 *
#347
0$
#348
1$
b01011010 (
